{"config":{"output_file":null,"full_docs":false,"pub_only":false,"reachable_only":false,"distro_crate":false,"signatures":false,"borrow_data":false},"version":"0.19.1","compilation":{"directory":"/Users/theo/Documents/rustacean-transformation/methods","program":"/Users/theo/.rustup/toolchains/stable-aarch64-apple-darwin/bin/rls","arguments":[],"output":"/Users/theo/Documents/rustacean-transformation/methods/target/rls/debug/deps/libmethods-ebc2597232a741d6.rmeta"},"prelude":{"crate_id":{"name":"methods","disambiguator":[16290214947819906787,0]},"crate_root":"src","external_crates":[{"file_name":"/Users/theo/Documents/rustacean-transformation/methods/src/main.rs","num":1,"id":{"name":"std","disambiguator":[9602236740471282608,0]}},{"file_name":"/Users/theo/Documents/rustacean-transformation/methods/src/main.rs","num":2,"id":{"name":"core","disambiguator":[16249227214258238047,0]}},{"file_name":"/Users/theo/Documents/rustacean-transformation/methods/src/main.rs","num":3,"id":{"name":"compiler_builtins","disambiguator":[13791225915815425008,0]}},{"file_name":"/Users/theo/Documents/rustacean-transformation/methods/src/main.rs","num":4,"id":{"name":"rustc_std_workspace_core","disambiguator":[455111089362928276,0]}},{"file_name":"/Users/theo/Documents/rustacean-transformation/methods/src/main.rs","num":5,"id":{"name":"alloc","disambiguator":[740641686899810413,0]}},{"file_name":"/Users/theo/Documents/rustacean-transformation/methods/src/main.rs","num":6,"id":{"name":"libc","disambiguator":[1452182208797737205,0]}},{"file_name":"/Users/theo/Documents/rustacean-transformation/methods/src/main.rs","num":7,"id":{"name":"unwind","disambiguator":[4474361821197688885,0]}},{"file_name":"/Users/theo/Documents/rustacean-transformation/methods/src/main.rs","num":8,"id":{"name":"cfg_if","disambiguator":[11146593528668201643,0]}},{"file_name":"/Users/theo/Documents/rustacean-transformation/methods/src/main.rs","num":9,"id":{"name":"hashbrown","disambiguator":[7026141623111916022,0]}},{"file_name":"/Users/theo/Documents/rustacean-transformation/methods/src/main.rs","num":10,"id":{"name":"rustc_std_workspace_alloc","disambiguator":[11096207044195207047,0]}},{"file_name":"/Users/theo/Documents/rustacean-transformation/methods/src/main.rs","num":11,"id":{"name":"std_detect","disambiguator":[16946906222655600942,0]}},{"file_name":"/Users/theo/Documents/rustacean-transformation/methods/src/main.rs","num":12,"id":{"name":"rustc_demangle","disambiguator":[9670608472714711915,0]}},{"file_name":"/Users/theo/Documents/rustacean-transformation/methods/src/main.rs","num":13,"id":{"name":"addr2line","disambiguator":[3075685271658393714,0]}},{"file_name":"/Users/theo/Documents/rustacean-transformation/methods/src/main.rs","num":14,"id":{"name":"gimli","disambiguator":[7553277853646633394,0]}},{"file_name":"/Users/theo/Documents/rustacean-transformation/methods/src/main.rs","num":15,"id":{"name":"object","disambiguator":[5387634511767759158,0]}},{"file_name":"/Users/theo/Documents/rustacean-transformation/methods/src/main.rs","num":16,"id":{"name":"memchr","disambiguator":[10401181353817371068,0]}},{"file_name":"/Users/theo/Documents/rustacean-transformation/methods/src/main.rs","num":17,"id":{"name":"panic_unwind","disambiguator":[14296571408058143832,0]}}],"span":{"file_name":"src/main.rs","byte_start":0,"byte_end":1081,"line_start":1,"line_end":52,"column_start":1,"column_end":2}},"imports":[],"defs":[{"kind":"Mod","id":{"krate":0,"index":0},"span":{"file_name":"src/main.rs","byte_start":0,"byte_end":1081,"line_start":1,"line_end":52,"column_start":1,"column_end":2},"name":"","qualname":"::","value":"src/main.rs","parent":null,"children":[{"krate":0,"index":1},{"krate":0,"index":2},{"krate":0,"index":9},{"krate":0,"index":12},{"krate":0,"index":3},{"krate":0,"index":8}],"decl_id":null,"docs":"","sig":null,"attributes":[]},{"kind":"Struct","id":{"krate":0,"index":9},"span":{"file_name":"src/main.rs","byte_start":24,"byte_end":33,"line_start":2,"line_end":2,"column_start":8,"column_end":17},"name":"Rectangle","qualname":"::Rectangle","value":"Rectangle { width, height }","parent":null,"children":[{"krate":0,"index":10},{"krate":0,"index":11}],"decl_id":null,"docs":"","sig":null,"attributes":[]},{"kind":"Field","id":{"krate":0,"index":10},"span":{"file_name":"src/main.rs","byte_start":40,"byte_end":45,"line_start":3,"line_end":3,"column_start":5,"column_end":10},"name":"width","qualname":"::Rectangle::width","value":"u32","parent":{"krate":0,"index":9},"children":[],"decl_id":null,"docs":"","sig":null,"attributes":[]},{"kind":"Field","id":{"krate":0,"index":11},"span":{"file_name":"src/main.rs","byte_start":56,"byte_end":62,"line_start":4,"line_end":4,"column_start":5,"column_end":11},"name":"height","qualname":"::Rectangle::height","value":"u32","parent":{"krate":0,"index":9},"children":[],"decl_id":null,"docs":"","sig":null,"attributes":[]},{"kind":"Local","id":{"krate":0,"index":1073741828},"span":{"file_name":"src/main.rs","byte_start":102,"byte_end":106,"line_start":8,"line_end":8,"column_start":14,"column_end":18},"name":"self","qualname":"<Rectangle>::area::self","value":"&Rectangle","parent":null,"children":[],"decl_id":null,"docs":"","sig":null,"attributes":[]},{"kind":"Method","id":{"krate":0,"index":4},"span":{"file_name":"src/main.rs","byte_start":96,"byte_end":100,"line_start":8,"line_end":8,"column_start":8,"column_end":12},"name":"area","qualname":"<Rectangle>::area","value":"fn area(&Self) -> u32","parent":null,"children":[],"decl_id":null,"docs":"","sig":null,"attributes":[]},{"kind":"Local","id":{"krate":0,"index":1073741829},"span":{"file_name":"src/main.rs","byte_start":170,"byte_end":174,"line_start":11,"line_end":11,"column_start":15,"column_end":19},"name":"self","qualname":"<Rectangle>::width::self","value":"&Rectangle","parent":null,"children":[],"decl_id":null,"docs":"","sig":null,"attributes":[]},{"kind":"Method","id":{"krate":0,"index":5},"span":{"file_name":"src/main.rs","byte_start":163,"byte_end":168,"line_start":11,"line_end":11,"column_start":8,"column_end":13},"name":"width","qualname":"<Rectangle>::width","value":"fn width(&Self) -> bool","parent":null,"children":[],"decl_id":null,"docs":"","sig":null,"attributes":[]},{"kind":"Local","id":{"krate":0,"index":1073741830},"span":{"file_name":"src/main.rs","byte_start":232,"byte_end":236,"line_start":14,"line_end":14,"column_start":18,"column_end":22},"name":"self","qualname":"<Rectangle>::can_hold::self","value":"&Rectangle","parent":null,"children":[],"decl_id":null,"docs":"","sig":null,"attributes":[]},{"kind":"Local","id":{"krate":0,"index":536870918},"span":{"file_name":"src/main.rs","byte_start":238,"byte_end":242,"line_start":14,"line_end":14,"column_start":24,"column_end":28},"name":"rect","qualname":"<Rectangle>::can_hold::rect","value":"&Rectangle","parent":null,"children":[],"decl_id":null,"docs":"","sig":null,"attributes":[]},{"kind":"Method","id":{"krate":0,"index":6},"span":{"file_name":"src/main.rs","byte_start":222,"byte_end":230,"line_start":14,"line_end":14,"column_start":8,"column_end":16},"name":"can_hold","qualname":"<Rectangle>::can_hold","value":"fn can_hold(&Self, &Rectangle) -> bool","parent":null,"children":[],"decl_id":null,"docs":"","sig":null,"attributes":[]},{"kind":"Local","id":{"krate":0,"index":1073741831},"span":{"file_name":"src/main.rs","byte_start":347,"byte_end":351,"line_start":17,"line_end":17,"column_start":15,"column_end":19},"name":"size","qualname":"<Rectangle>::sqaure::size","value":"u32","parent":null,"children":[],"decl_id":null,"docs":"","sig":null,"attributes":[]},{"kind":"Method","id":{"krate":0,"index":7},"span":{"file_name":"src/main.rs","byte_start":340,"byte_end":346,"line_start":17,"line_end":17,"column_start":8,"column_end":14},"name":"sqaure","qualname":"<Rectangle>::sqaure","value":"fn sqaure(u32) -> Rectangle","parent":null,"children":[],"decl_id":null,"docs":"","sig":null,"attributes":[]},{"kind":"Function","id":{"krate":0,"index":8},"span":{"file_name":"src/main.rs","byte_start":466,"byte_end":470,"line_start":25,"line_end":25,"column_start":4,"column_end":8},"name":"main","qualname":"::main","value":"fn main()","parent":null,"children":[],"decl_id":null,"docs":"","sig":null,"attributes":[]},{"kind":"Local","id":{"krate":0,"index":2415919112},"span":{"file_name":"src/main.rs","byte_start":483,"byte_end":488,"line_start":26,"line_end":26,"column_start":9,"column_end":14},"name":"rect1","qualname":"rect1$HirId { owner: DefId(0:8 ~ methods[e212]::main), local_id: 9 }","value":"Rectangle","parent":null,"children":[],"decl_id":null,"docs":"","sig":null,"attributes":[]},{"kind":"Local","id":{"krate":0,"index":1207959560},"span":{"file_name":"src/main.rs","byte_start":557,"byte_end":562,"line_start":30,"line_end":30,"column_start":9,"column_end":14},"name":"rect2","qualname":"rect2$HirId { owner: DefId(0:8 ~ methods[e212]::main), local_id: 18 }","value":"Rectangle","parent":null,"children":[],"decl_id":null,"docs":"","sig":null,"attributes":[]},{"kind":"Local","id":{"krate":0,"index":3623878664},"span":{"file_name":"src/main.rs","byte_start":631,"byte_end":636,"line_start":34,"line_end":34,"column_start":9,"column_end":14},"name":"rect3","qualname":"rect3$HirId { owner: DefId(0:8 ~ methods[e212]::main), local_id: 27 }","value":"Rectangle","parent":null,"children":[],"decl_id":null,"docs":"","sig":null,"attributes":[]},{"kind":"Local","id":{"krate":0,"index":1124073480},"span":{"file_name":"src/main.rs","byte_start":1047,"byte_end":1054,"line_start":51,"line_end":51,"column_start":9,"column_end":16},"name":"square1","qualname":"square1$HirId { owner: DefId(0:8 ~ methods[e212]::main), local_id: 194 }","value":"Rectangle","parent":null,"children":[],"decl_id":null,"docs":"","sig":null,"attributes":[]}],"impls":[{"id":0,"kind":"Inherent","span":{"file_name":"src/main.rs","byte_start":77,"byte_end":86,"line_start":7,"line_end":7,"column_start":6,"column_end":15},"value":"","parent":null,"children":[{"krate":0,"index":4},{"krate":0,"index":5},{"krate":0,"index":6},{"krate":0,"index":7}],"docs":"","sig":null,"attributes":[]}],"refs":[{"kind":"Variable","span":{"file_name":"src/main.rs","byte_start":40,"byte_end":45,"line_start":3,"line_end":3,"column_start":5,"column_end":10},"ref_id":{"krate":0,"index":10}},{"kind":"Variable","span":{"file_name":"src/main.rs","byte_start":56,"byte_end":62,"line_start":4,"line_end":4,"column_start":5,"column_end":11},"ref_id":{"krate":0,"index":11}},{"kind":"Type","span":{"file_name":"src/main.rs","byte_start":77,"byte_end":86,"line_start":7,"line_end":7,"column_start":6,"column_end":15},"ref_id":{"krate":0,"index":9}},{"kind":"Variable","span":{"file_name":"src/main.rs","byte_start":125,"byte_end":129,"line_start":9,"line_end":9,"column_start":9,"column_end":13},"ref_id":{"krate":0,"index":1073741828}},{"kind":"Variable","span":{"file_name":"src/main.rs","byte_start":130,"byte_end":136,"line_start":9,"line_end":9,"column_start":14,"column_end":20},"ref_id":{"krate":0,"index":11}},{"kind":"Variable","span":{"file_name":"src/main.rs","byte_start":139,"byte_end":143,"line_start":9,"line_end":9,"column_start":23,"column_end":27},"ref_id":{"krate":0,"index":1073741828}},{"kind":"Variable","span":{"file_name":"src/main.rs","byte_start":144,"byte_end":149,"line_start":9,"line_end":9,"column_start":28,"column_end":33},"ref_id":{"krate":0,"index":10}},{"kind":"Variable","span":{"file_name":"src/main.rs","byte_start":194,"byte_end":198,"line_start":12,"line_end":12,"column_start":9,"column_end":13},"ref_id":{"krate":0,"index":1073741829}},{"kind":"Variable","span":{"file_name":"src/main.rs","byte_start":199,"byte_end":204,"line_start":12,"line_end":12,"column_start":14,"column_end":19},"ref_id":{"krate":0,"index":10}},{"kind":"Type","span":{"file_name":"src/main.rs","byte_start":245,"byte_end":254,"line_start":14,"line_end":14,"column_start":31,"column_end":40},"ref_id":{"krate":0,"index":9}},{"kind":"Variable","span":{"file_name":"src/main.rs","byte_start":274,"byte_end":278,"line_start":15,"line_end":15,"column_start":9,"column_end":13},"ref_id":{"krate":0,"index":1073741830}},{"kind":"Variable","span":{"file_name":"src/main.rs","byte_start":279,"byte_end":284,"line_start":15,"line_end":15,"column_start":14,"column_end":19},"ref_id":{"krate":0,"index":10}},{"kind":"Variable","span":{"file_name":"src/main.rs","byte_start":287,"byte_end":291,"line_start":15,"line_end":15,"column_start":22,"column_end":26},"ref_id":{"krate":0,"index":536870918}},{"kind":"Variable","span":{"file_name":"src/main.rs","byte_start":292,"byte_end":297,"line_start":15,"line_end":15,"column_start":27,"column_end":32},"ref_id":{"krate":0,"index":10}},{"kind":"Variable","span":{"file_name":"src/main.rs","byte_start":301,"byte_end":305,"line_start":15,"line_end":15,"column_start":36,"column_end":40},"ref_id":{"krate":0,"index":1073741830}},{"kind":"Variable","span":{"file_name":"src/main.rs","byte_start":306,"byte_end":312,"line_start":15,"line_end":15,"column_start":41,"column_end":47},"ref_id":{"krate":0,"index":11}},{"kind":"Variable","span":{"file_name":"src/main.rs","byte_start":315,"byte_end":319,"line_start":15,"line_end":15,"column_start":50,"column_end":54},"ref_id":{"krate":0,"index":536870918}},{"kind":"Variable","span":{"file_name":"src/main.rs","byte_start":320,"byte_end":326,"line_start":15,"line_end":15,"column_start":55,"column_end":61},"ref_id":{"krate":0,"index":11}},{"kind":"Type","span":{"file_name":"src/main.rs","byte_start":361,"byte_end":370,"line_start":17,"line_end":17,"column_start":29,"column_end":38},"ref_id":{"krate":0,"index":9}},{"kind":"Type","span":{"file_name":"src/main.rs","byte_start":381,"byte_end":390,"line_start":18,"line_end":18,"column_start":9,"column_end":18},"ref_id":{"krate":0,"index":9}},{"kind":"Variable","span":{"file_name":"src/main.rs","byte_start":405,"byte_end":410,"line_start":19,"line_end":19,"column_start":13,"column_end":18},"ref_id":{"krate":0,"index":10}},{"kind":"Variable","span":{"file_name":"src/main.rs","byte_start":412,"byte_end":416,"line_start":19,"line_end":19,"column_start":20,"column_end":24},"ref_id":{"krate":0,"index":1073741831}},{"kind":"Variable","span":{"file_name":"src/main.rs","byte_start":430,"byte_end":436,"line_start":20,"line_end":20,"column_start":13,"column_end":19},"ref_id":{"krate":0,"index":11}},{"kind":"Variable","span":{"file_name":"src/main.rs","byte_start":438,"byte_end":442,"line_start":20,"line_end":20,"column_start":21,"column_end":25},"ref_id":{"krate":0,"index":1073741831}},{"kind":"Type","span":{"file_name":"src/main.rs","byte_start":491,"byte_end":500,"line_start":26,"line_end":26,"column_start":17,"column_end":26},"ref_id":{"krate":0,"index":9}},{"kind":"Variable","span":{"file_name":"src/main.rs","byte_start":511,"byte_end":516,"line_start":27,"line_end":27,"column_start":9,"column_end":14},"ref_id":{"krate":0,"index":10}},{"kind":"Variable","span":{"file_name":"src/main.rs","byte_start":530,"byte_end":536,"line_start":28,"line_end":28,"column_start":9,"column_end":15},"ref_id":{"krate":0,"index":11}},{"kind":"Type","span":{"file_name":"src/main.rs","byte_start":565,"byte_end":574,"line_start":30,"line_end":30,"column_start":17,"column_end":26},"ref_id":{"krate":0,"index":9}},{"kind":"Variable","span":{"file_name":"src/main.rs","byte_start":585,"byte_end":590,"line_start":31,"line_end":31,"column_start":9,"column_end":14},"ref_id":{"krate":0,"index":10}},{"kind":"Variable","span":{"file_name":"src/main.rs","byte_start":604,"byte_end":610,"line_start":32,"line_end":32,"column_start":9,"column_end":15},"ref_id":{"krate":0,"index":11}},{"kind":"Type","span":{"file_name":"src/main.rs","byte_start":639,"byte_end":648,"line_start":34,"line_end":34,"column_start":17,"column_end":26},"ref_id":{"krate":0,"index":9}},{"kind":"Variable","span":{"file_name":"src/main.rs","byte_start":659,"byte_end":664,"line_start":35,"line_end":35,"column_start":9,"column_end":14},"ref_id":{"krate":0,"index":10}},{"kind":"Variable","span":{"file_name":"src/main.rs","byte_start":678,"byte_end":684,"line_start":36,"line_end":36,"column_start":9,"column_end":15},"ref_id":{"krate":0,"index":11}},{"kind":"Function","span":{"file_name":"src/main.rs","byte_start":783,"byte_end":787,"line_start":41,"line_end":41,"column_start":15,"column_end":19},"ref_id":{"krate":0,"index":4}},{"kind":"Variable","span":{"file_name":"src/main.rs","byte_start":777,"byte_end":782,"line_start":41,"line_end":41,"column_start":9,"column_end":14},"ref_id":{"krate":0,"index":2415919112}},{"kind":"Function","span":{"file_name":"src/main.rs","byte_start":811,"byte_end":816,"line_start":44,"line_end":44,"column_start":14,"column_end":19},"ref_id":{"krate":0,"index":5}},{"kind":"Variable","span":{"file_name":"src/main.rs","byte_start":805,"byte_end":810,"line_start":44,"line_end":44,"column_start":8,"column_end":13},"ref_id":{"krate":0,"index":2415919112}},{"kind":"Variable","span":{"file_name":"src/main.rs","byte_start":885,"byte_end":890,"line_start":45,"line_end":45,"column_start":65,"column_end":70},"ref_id":{"krate":0,"index":2415919112}},{"kind":"Variable","span":{"file_name":"src/main.rs","byte_start":891,"byte_end":896,"line_start":45,"line_end":45,"column_start":71,"column_end":76},"ref_id":{"krate":0,"index":10}},{"kind":"Function","span":{"file_name":"src/main.rs","byte_start":953,"byte_end":961,"line_start":48,"line_end":48,"column_start":48,"column_end":56},"ref_id":{"krate":0,"index":6}},{"kind":"Variable","span":{"file_name":"src/main.rs","byte_start":947,"byte_end":952,"line_start":48,"line_end":48,"column_start":42,"column_end":47},"ref_id":{"krate":0,"index":2415919112}},{"kind":"Variable","span":{"file_name":"src/main.rs","byte_start":963,"byte_end":968,"line_start":48,"line_end":48,"column_start":58,"column_end":63},"ref_id":{"krate":0,"index":1207959560}},{"kind":"Function","span":{"file_name":"src/main.rs","byte_start":1019,"byte_end":1027,"line_start":49,"line_end":49,"column_start":48,"column_end":56},"ref_id":{"krate":0,"index":6}},{"kind":"Variable","span":{"file_name":"src/main.rs","byte_start":1013,"byte_end":1018,"line_start":49,"line_end":49,"column_start":42,"column_end":47},"ref_id":{"krate":0,"index":2415919112}},{"kind":"Variable","span":{"file_name":"src/main.rs","byte_start":1029,"byte_end":1034,"line_start":49,"line_end":49,"column_start":58,"column_end":63},"ref_id":{"krate":0,"index":3623878664}},{"kind":"Function","span":{"file_name":"src/main.rs","byte_start":1068,"byte_end":1074,"line_start":51,"line_end":51,"column_start":30,"column_end":36},"ref_id":{"krate":0,"index":7}},{"kind":"Type","span":{"file_name":"src/main.rs","byte_start":1057,"byte_end":1066,"line_start":51,"line_end":51,"column_start":19,"column_end":28},"ref_id":{"krate":0,"index":9}}],"macro_refs":[],"relations":[{"span":{"file_name":"src/main.rs","byte_start":77,"byte_end":86,"line_start":7,"line_end":7,"column_start":6,"column_end":15},"kind":{"Impl":{"id":0}},"from":{"krate":0,"index":9},"to":{"krate":4294967295,"index":4294967295}}]}